{
// general
    "workbench.colorTheme": "Monokai Dimmed",
    "files.autoSave": "afterDelay",
    // editor
    "editor.autoClosingBrackets": "never",
    "editor.autoSurround": "never",
    "editor.acceptSuggestionOnEnter": "off",
    "editor.autoClosingComments": "never",
    "editor.autoClosingQuotes": "never",
    "editor.autoClosingDelete": "never",
    "editor.autoClosingOvertype": "never",
    "editor.suggest.selectionMode": "never",
    
// powershell
    "powershell.promptToUpdatePowerShell": false,

// typescript
    "typescript.suggest.enabled": false,
    
// js
    "javascript.suggest.enabled": false,
    
// py
    "python.autoComplete.extraPaths": [
        
    ]
}